cetk/__init__.py
cetk/db.py
cetk/logging.py
cetk/settings.py
cetk/utils.py
cetk/edb/__init__.py
cetk/edb/apps.py
cetk/edb/cache.py
cetk/edb/const.py
cetk/edb/copy.py
cetk/edb/exporters.py
cetk/edb/ltreefield.py
cetk/edb/signals.py
cetk/edb/traffic.py
cetk/edb/units.py
cetk/edb/utils.py
cetk/edb/fixtures/edb-ref.json
cetk/edb/importers/__init__.py
cetk/edb/importers/activity_import.py
cetk/edb/importers/codeset_import.py
cetk/edb/importers/gridsource_import.py
cetk/edb/importers/roadsource_import.py
cetk/edb/importers/source_import.py
cetk/edb/importers/timevar_import.py
cetk/edb/importers/utils.py
cetk/edb/importers/validation.py
cetk/edb/migrations/0001_initial.py
cetk/edb/migrations/0002_data.py
cetk/edb/migrations/0003_create_gpkg_tables.py
cetk/edb/migrations/__init__.py
cetk/edb/models/__init__.py
cetk/edb/models/base.py
cetk/edb/models/common_models.py
cetk/edb/models/fleets.py
cetk/edb/models/gridsource_models.py
cetk/edb/models/road_classes.py
cetk/edb/models/road_models.py
cetk/edb/models/source_models.py
cetk/edb/models/timevar_models.py
cetk/edb/rasterize/__init__.py
cetk/edb/rasterize/rasterizer.py
cetk/emissions/__init__.py
cetk/emissions/aggregate_emissions.sql
cetk/emissions/areasource_emissions.sql
cetk/emissions/calc.py
cetk/emissions/filters.py
cetk/emissions/gridsource_emissions.sql
cetk/emissions/pointsource_emissions.sql
cetk/emissions/queries.py
cetk/emissions/roadsource_emissions.sql
cetk/emissions/used_substances.sql
cetk/emissions/views.py
cetk/tools/__init__.py
cetk/tools/cetk_command.py
cetk/tools/manage.py
cetk/tools/utils.py
cetk-0.0.7.dev0.dist-info/licenses/LICENSE
cetk-0.0.7.dev0.dist-info/METADATA
cetk-0.0.7.dev0.dist-info/WHEEL
cetk-0.0.7.dev0.dist-info/entry_points.txt
cetk-0.0.7.dev0.dist-info/top_level.txt
cetk-0.0.7.dev0.dist-info/RECORD
