Metadata-Version: 2.4
Name: cetk
Version: 0.0.7.dev0
Summary: CLAIRs Emission ToolKit cetk
Author: Christian Asker, Mattias Jakobsson, David Segersson, Eef van Dongen
Maintainer-email: FO Luft <foluftadmin@smhi.se>
License-Expression: Apache-2.0
Classifier: Programming Language :: Python :: 3
Classifier: Topic :: Scientific/Engineering :: Atmospheric Science
Requires-Python: >=3.9
License-File: LICENSE
Requires-Dist: django<6,>=4.2
Requires-Dist: fiona>=1.8.18
Requires-Dist: geopandas>=0.12
Requires-Dist: netCDF4>=1.5.4
Requires-Dist: numpy>=1.20.3
Requires-Dist: openpyxl>=3.0.7
Requires-Dist: pandas>=2.0
Requires-Dist: pyogrio>=0.4.2
Requires-Dist: rastafari2>=0.4
Requires-Dist: rasterio>=1.3
Requires-Dist: shapely>=2.0
Dynamic: license-file
